resolvent4py/__init__.py
resolvent4py/linalg/__init__.py
resolvent4py/linalg/eigendecomposition.py
resolvent4py/linalg/randomized_svd.py
resolvent4py/linalg/resolvent_analysis_time_stepping.py
resolvent4py/linear_operators/__init__.py
resolvent4py/linear_operators/linear_operator.py
resolvent4py/linear_operators/low_rank.py
resolvent4py/linear_operators/low_rank_updated.py
resolvent4py/linear_operators/matrix.py
resolvent4py/linear_operators/product.py
resolvent4py/linear_operators/projection.py
resolvent4py/model_reduction/__init__.py
resolvent4py/model_reduction/balanced_truncation.py
resolvent4py/utils/__init__.py
resolvent4py/utils/bv.py
resolvent4py/utils/comms.py
resolvent4py/utils/errors.py
resolvent4py/utils/io.py
resolvent4py/utils/ksp.py
resolvent4py/utils/matrix.py
resolvent4py/utils/miscellaneous.py
resolvent4py/utils/random.py
resolvent4py/utils/vector.py
resolvent4py-1.0.1.dist-info/licenses/LICENSE
resolvent4py-1.0.1.dist-info/METADATA
resolvent4py-1.0.1.dist-info/WHEEL
resolvent4py-1.0.1.dist-info/top_level.txt
resolvent4py-1.0.1.dist-info/RECORD
