Metadata-Version: 2.4
Name: resolvent4py
Version: 1.0.1
Summary: A parallel Python-based library for analysis, model reduction and control of large-scale linear systems.
Author-email: Alberto Padovan <alberto.padovan.94@gmail.com>, Vishal Anantharaman <vanantha@caltech.edu>, Clancy Rowley <cwrowley@princeton.edu>
License-Expression: MIT
Project-URL: Homepage, https://github.com/albertopadovan/resolvent4py
Project-URL: Documentation, https://albertopadovan.github.io/resolvent4py/
Keywords: linear systems,parallel computing,MPI,PETSc,SLEPc,resolvent analysis,harmonic resolvent analysis,model reduction,control
Requires-Python: >=3.10
License-File: LICENSE
Requires-Dist: numpy
Requires-Dist: scipy
Requires-Dist: matplotlib
Provides-Extra: docs
Requires-Dist: sphinx; extra == "docs"
Requires-Dist: sphinx-rtd-theme; extra == "docs"
Requires-Dist: sphinx-gallery; extra == "docs"
Requires-Dist: sphinxcontrib-bibtex; extra == "docs"
Dynamic: license-file
